spark_data_frame_comparer/__init__.py
spark_data_frame_comparer/list_utils.py
spark_data_frame_comparer/py.typed
spark_data_frame_comparer/schema_comparer.py
spark_data_frame_comparer/schema_comparison_item.py
spark_data_frame_comparer/sparjk_data_frame_comparer_generic_exception.py
spark_data_frame_comparer/spark_data_frame_comparer.py
spark_data_frame_comparer/spark_data_frame_comparer_exception.py
spark_data_frame_comparer/spark_data_frame_comparer_helper.py
spark_data_frame_comparer/spark_data_frame_error.py
spark_data_frame_comparer/spark_data_frame_exception_type.py
spark_data_frame_comparer/spark_data_frame_sorter.py
spark_data_frame_comparer/utilities/__init__.py
spark_data_frame_comparer/utilities/dictionary_joiner/__init__.py
spark_data_frame_comparer/utilities/dictionary_joiner/dictionary_joiner.py
spark_data_frame_comparer/utilities/dictionary_joiner/joined_result.py
spark_data_frame_comparer/utilities/pretty_print/__init__.py
spark_data_frame_comparer/utilities/pretty_print/pretty_print.py
sparkdataframecomparer-2.0.15.dist-info/licenses/LICENSE
tests/__init__.py
tests/conftest.py
tests/data_frame_sorter/__init__.py
tests/data_frame_sorter/test_data_frame_sorter.py
tests/data_frame_sorter/input/__init__.py
tests/schema_comparer/__init__.py
tests/schema_comparer/matches/__init__.py
tests/schema_comparer/matches/test_schema_comparer_array_to_array.py
tests/schema_comparer/matches/test_schema_comparer_array_to_array_allow_missing_nullable_properties_fail.py
tests/schema_comparer/matches/test_schema_comparer_array_to_array_allow_missing_nullable_properties_pass.py
tests/schema_comparer/matches/test_schema_comparer_simple.py
tests/schema_comparer/matches/test_schema_comparer_struct_to_struct_nullable_parent.py
tests/schema_comparer/matches/test_schema_comparer_struct_to_struct_nullable_parent_recursive.py
tests/schema_comparer/not_matches/__init__.py
tests/schema_comparer/not_matches/test_schema_comparer_array_to_array.py
tests/schema_comparer/not_matches/test_schema_comparer_complex.py
sparkdataframecomparer-2.0.15.dist-info/METADATA
sparkdataframecomparer-2.0.15.dist-info/WHEEL
sparkdataframecomparer-2.0.15.dist-info/top_level.txt
sparkdataframecomparer-2.0.15.dist-info/RECORD
