Metadata-Version: 2.4
Name: sparkdataframecomparer
Version: 2.0.15
Summary: Deep Comparer for Spark Data Frames
Home-page: https://github.com/imranq2/sparkdataframecomparer
Author: Imran Qureshi
Author-email: imranq2@hotmail.com
Classifier: Development Status :: 4 - Beta
Classifier: Programming Language :: Python :: 3
Classifier: License :: OSI Approved :: Apache Software License
Classifier: Operating System :: OS Independent
Requires-Python: >=3
License-File: LICENSE
Requires-Dist: logger>=1.4
Provides-Extra: spark
Requires-Dist: py4j==0.10.9.7; extra == "spark"
Requires-Dist: pyspark==3.5.5; extra == "spark"
Dynamic: author
Dynamic: author-email
Dynamic: classifier
Dynamic: description
Dynamic: description-content-type
Dynamic: home-page
Dynamic: license-file
Dynamic: provides-extra
Dynamic: requires-dist
Dynamic: requires-python
Dynamic: summary
